{
  "manufacturers": [
    "Apple",
    "Samsung",
    "Huawei",
    "Xiaomi",
    "Oppo",
    "Vivo",
    "OnePlus",
    "Google",
    "Sony",
    "LG",
    "Nokia",
    "Motorola",
    "Realme",
    "Honor",
    "Asus",
    "ZTE",
    "Meizu",
    "Lenovo",
    "Tecno",
    "Infinix",
    "Itel",
    "BlackBerry",
    "Panasonic",
    "Sharp",
    "Alcatel"
  ],
  "aliases": {
    "iPhone": "Apple",
    "iPad": "Apple",
    "Pixel": "Google",
    "Galaxy": "Samsung",
    "Xperia": "Sony",
    "Redmi": "Xiaomi",
    "Mi": "Xiaomi",
    "Honor": "Honor",
    "Moto": "Motorola",
    "Nexus": "Google",
    "Zenfone": "Asus"
  },
  "name_hints": [
    "iphone",
    "ipad",
    "android",
    "pixel",
    "galaxy",
    "xperia",
    "redmi",
    "mi ",
    "honor",
    "moto",
    "nexus",
    "zenfone"
  ],
  "id_hints": [
    "adb",
    "android",
    "iphone",
    "ios",
    "ipad",
    "com.apple.avfoundation",
    "avfoundation",
    "ip",
    "rtsp",
    "rtmp",
    "ndihx",
    "ndi",
    "droidcam",
    "epoccam",
    "ivcam"
  ]
}
